svs_core/__init__.py
svs_core/__main__.py
svs_core/apps.py
svs_core/cli/lib.py
svs_core/cli/service.py
svs_core/cli/state.py
svs_core/cli/template.py
svs_core/cli/user.py
svs_core/cli/utils.py
svs_core/db/__init__.py
svs_core/db/models.py
svs_core/db/settings.py
svs_core/db/fixtures/devuser.py
svs_core/db/migrations/0001_initial.py
svs_core/db/migrations/0002_usergroupmodel.py
svs_core/db/migrations/0003_templatemodel_docs_url.py
svs_core/db/migrations/__init__.py
svs_core/docker/__init__.py
svs_core/docker/base.py
svs_core/docker/container.py
svs_core/docker/image.py
svs_core/docker/json_properties.py
svs_core/docker/network.py
svs_core/docker/service.py
svs_core/docker/template.py
svs_core/shared/__init__.py
svs_core/shared/env_manager.py
svs_core/shared/exceptions.py
svs_core/shared/git_source.py
svs_core/shared/hash.py
svs_core/shared/http.py
svs_core/shared/logger.py
svs_core/shared/ports.py
svs_core/shared/shell.py
svs_core/shared/text.py
svs_core/shared/volumes.py
svs_core/users/__init__.py
svs_core/users/system.py
svs_core/users/user.py
svs_core/users/user_group.py
svs_core-0.12.0.dist-info/licenses/LICENSE
svs_core-0.12.0.dist-info/METADATA
svs_core-0.12.0.dist-info/WHEEL
svs_core-0.12.0.dist-info/entry_points.txt
svs_core-0.12.0.dist-info/top_level.txt
svs_core-0.12.0.dist-info/RECORD
