Metadata-Version: 2.4
Name: svs_core
Version: 0.12.0
Summary: Core library for SVS
Author-email: Kristián Kunc <diist7i4c@mozmail.com>
Requires-Python: >=3.13
License-File: LICENSE
Requires-Dist: bcrypt==5.0.0
Requires-Dist: docker==7.1.0
Requires-Dist: httpx==0.28.1
Requires-Dist: typer==0.21.1
Requires-Dist: Django==6.0.1
Requires-Dist: dj_database_url==3.1.0
Requires-Dist: psycopg2==2.9.11
Provides-Extra: dev
Requires-Dist: black==26.1.0; extra == "dev"
Requires-Dist: isort==7.0.0; extra == "dev"
Requires-Dist: mypy==1.19.1; extra == "dev"
Requires-Dist: pre-commit==4.5.1; extra == "dev"
Requires-Dist: pytest==9.0.2; extra == "dev"
Requires-Dist: pytest-asyncio==1.3.0; extra == "dev"
Requires-Dist: pytest-cov==7.0.0; extra == "dev"
Requires-Dist: pytest-dotenv==0.5.2; extra == "dev"
Requires-Dist: pytest_mock==3.15.1; extra == "dev"
Requires-Dist: ruff==0.14.14; extra == "dev"
Requires-Dist: twine==6.2.0; extra == "dev"
Requires-Dist: pytest-django==4.11.1; extra == "dev"
Provides-Extra: docs
Requires-Dist: zensical==0.0.20; extra == "docs"
Requires-Dist: mkdocstrings[python]==1.0.2; extra == "docs"
Requires-Dist: mkdocs-awesome-nav==3.3.0; extra == "docs"
Requires-Dist: mkdocs-pdf==0.1.2; extra == "docs"
Dynamic: license-file
